watchYoutube/__init__.py
watchYoutube/youtube.py
watchyoutube-0.0.13.dist-info/LICENSE
watchyoutube-0.0.13.dist-info/METADATA
watchyoutube-0.0.13.dist-info/WHEEL
watchyoutube-0.0.13.dist-info/top_level.txt
watchyoutube-0.0.13.dist-info/RECORD
