Metadata-Version: 2.1
Name: watchyoutube
Version: 0.0.13
Summary: Streaming video data via networks
Home-page: UNKNOWN
Author: Ibrahima SOUMARE
Author-email: soumareiibrahima@gmail.com
License: UNKNOWN
Keywords: video
Platform: UNKNOWN
Classifier: Development Status :: 1 - Planning
